CHANGES.rst
CONTRIBUTORS.rst
MANIFEST.in
README.rst
setup.cfg
setup.py
docs/LICENSE.GPL
docs/LICENSE.rst
docs/index.rst
src/cpskin/__init__.py
src/cpskin.caching.egg-info/PKG-INFO
src/cpskin.caching.egg-info/SOURCES.txt
src/cpskin.caching.egg-info/dependency_links.txt
src/cpskin.caching.egg-info/entry_points.txt
src/cpskin.caching.egg-info/namespace_packages.txt
src/cpskin.caching.egg-info/not-zip-safe
src/cpskin.caching.egg-info/requires.txt
src/cpskin.caching.egg-info/top_level.txt
src/cpskin/caching/__init__.py
src/cpskin/caching/configure.zcml
src/cpskin/caching/hooks.py
src/cpskin/caching/interfaces.py
src/cpskin/caching/patch.py
src/cpskin/caching/purge.py
src/cpskin/caching/rewrite.py
src/cpskin/caching/setuphandlers.py
src/cpskin/caching/testing.py
src/cpskin/caching/upgrades.py
src/cpskin/caching/browser/__init__.py
src/cpskin/caching/browser/configure.zcml
src/cpskin/caching/browser/overrides/.gitkeep
src/cpskin/caching/browser/static/.gitkeep
src/cpskin/caching/locales/cpskin.caching.pot
src/cpskin/caching/locales/update.sh
src/cpskin/caching/profiles/default/browserlayer.xml
src/cpskin/caching/profiles/default/cpskincaching_default.txt
src/cpskin/caching/profiles/default/metadata.xml
src/cpskin/caching/profiles/default/registry.xml
src/cpskin/caching/tests/__init__.py
src/cpskin/caching/tests/minisites_config.txt
src/cpskin/caching/tests/test_hooks.py
src/cpskin/caching/tests/test_rewrite.py
src/cpskin/caching/tests/test_robot.py
src/cpskin/caching/tests/test_setup.py
src/cpskin/caching/tests/robot/test_example.robot