Metadata-Version: 2.1
Name: cpskin.caching
Version: 1.1.3
Summary: Caching configuration for cpskin
Home-page: https://pypi.python.org/pypi/cpskin.caching
Author: Jean-Francois Roche
Author-email: jfroche@affinitic.be
License: GPL version 2
Keywords: Python Plone
Platform: UNKNOWN
Classifier: Environment :: Web Environment
Classifier: Framework :: Plone
Classifier: Framework :: Plone :: 4.3
Classifier: Programming Language :: Python
Classifier: Programming Language :: Python :: 2.7
Classifier: Operating System :: OS Independent
Classifier: License :: OSI Approved :: GNU General Public License v2 (GPLv2)
Provides-Extra: test
